setup.py
sloev_wsrpc.egg-info/PKG-INFO
sloev_wsrpc.egg-info/SOURCES.txt
sloev_wsrpc.egg-info/dependency_links.txt
sloev_wsrpc.egg-info/pbr.json
sloev_wsrpc.egg-info/requires.txt
sloev_wsrpc.egg-info/top_level.txt
wsrpc/__init__.py
wsrpc/_version.py
wsrpc/auth.py
wsrpc/handler.py
wsrpc/server.py