Metadata-Version: 1.0
Name: sloev-wsrpc
Version: 0.6
Summary: decorator based websocket rpc using tornado
Home-page: https://github.com/sloev/wsrpc
Author: sloev
Author-email: johannesgj@gmail.com
License: MIT License
Platform: UNKNOWN
